ugrapheme/justify.pxd
ugrapheme/uprop.pxd
ugrapheme/graphemes.cpython-313-i386-linux-gnu.so
ugrapheme/graphemes.pxd
ugrapheme/offsets.cpython-313-i386-linux-gnu.so
ugrapheme/justify.pyx
ugrapheme/justify.cpython-313-i386-linux-gnu.so
ugrapheme/graphemes.pyx
ugrapheme/__init__.py
ugrapheme/iterate.cpython-313-i386-linux-gnu.so
ugrapheme/ugrapheme.pyx
ugrapheme/offsets.pxd
ugrapheme/alloc.cpython-313-i386-linux-gnu.so
ugrapheme/iterate.pxd
ugrapheme/ugrapheme.pxd
ugrapheme/alloc.pxd
ugrapheme/iterate.pyx
ugrapheme/ugrapheme.cpython-313-i386-linux-gnu.so
ugrapheme/latin1.pxd
ugrapheme/offsets.pyx
ugrapheme/__init__.pxd
ugrapheme/kk_copy.pxd
ugrapheme/unicode_pyobject.pxd
ugrapheme/alloc.pyx
ugrapheme/diag.pyx
ugrapheme/tables/control.pxd
ugrapheme/tables/prepend.pxd
ugrapheme/tables/__init__.py
ugrapheme/tables/postcore.pxd
ugrapheme/tables/incb.pxd
ugrapheme/tables/extend.pxd
ugrapheme/tables/__init__.pxd
ugrapheme/tables/xpicto.pxd
ugrapheme-0.8.dist-info/top_level.txt
ugrapheme-0.8.dist-info/RECORD
ugrapheme-0.8.dist-info/LICENSE
ugrapheme-0.8.dist-info/METADATA
ugrapheme-0.8.dist-info/WHEEL
