Metadata-Version: 2.1
Name: ugrapheme
Version: 0.8
Summary: Unicode 16.0 Extended grapheme clusters in nanoseconds
Author: !ZAJC!
License: BSD Zero Clause License
Project-URL: Homepage, https://github.com/Z4JC/ugrapheme
Classifier: Development Status :: 5 - Production/Stable
Classifier: Intended Audience :: Developers
Classifier: License :: OSI Approved :: Zero-Clause BSD (0BSD)
Classifier: Programming Language :: Python :: 3
Classifier: Programming Language :: Cython
Classifier: Topic :: Software Development :: Libraries :: Python Modules
Classifier: Topic :: Software Development :: Internationalization
Classifier: Topic :: Software Development :: Localization
Classifier: Topic :: Text Processing
Classifier: Topic :: Terminals
Classifier: Topic :: Utilities
License-File: LICENSE
Requires-Dist: uwcwidth
Provides-Extra: test
Requires-Dist: pytest; extra == "test"
